[{"_path":"/indonesie-2015/day-8-back-to-yogyakarta","title":"Day 8 - Back to Yogyakarta","excerpt":"Dat was helaas weer n vreselijke nacht. 30'C.. Ook al stond de ventilator de heletijd aan. Nu terug naar Yogyakarta...","date":"2015-10-18","category":"Jakarta, Yogjakarta, Bali - Indonesie"},{"_path":"/indonesie-2015/day-10-train-trip-east-java","title":"Day 10 - Train trip, East Java","excerpt":"Een lange dag vol met avontuur reizen. We nemen de trein van Yogyakarta naar Probolingo, deze rit duurde 9 uur...","date":"2015-10-20","category":"Jakarta, Yogjakarta, Bali - Indonesie"}]