[{"_path":"/indonesie-2015/day-11-penanjakan-viewpoint-mt-bromo-probolingo","_dir":"indonesie-2015","_draft":false,"_partial":false,"_locale":"","title":"Day 11 - Penanjakan Viewpoint & Mt. Bromo, Probolinggo, East Java","description":"Sheeet, het was vroeg, 3:30u. Meteen de jeep in die nog verder de hoogte in scheurde...","date":"2015-10-21","image":"https://www.danhnguyen.nl/wp-content/uploads/image188.jpg","category":"Jakarta, Yogjakarta, Bali - Indonesie","_type":"markdown","_id":"content:indonesie-2015:day-11-penanjakan-viewpoint-mt-bromo-probolingo.md","_source":"content","_file":"indonesie-2015/day-11-penanjakan-viewpoint-mt-bromo-probolingo.md","_extension":"md"},{"_path":"/indonesie-2015/day-13-lovina-beach-bali","_dir":"indonesie-2015","_draft":false,"_partial":false,"_locale":"","title":"Day 13 - Lovina Beach, Bali","description":"Voordat we naar Bali gaan, eerst baby turtles vrijlaten in de zee. Cute cute...","date":"2015-10-24","image":"https://www.danhnguyen.nl/wp-content/uploads/image257.jpg","category":"Jakarta, Yogjakarta, Bali - Indonesie","_type":"markdown","_id":"content:indonesie-2015:day-13-lovina-beach-bali.md","_source":"content","_file":"indonesie-2015/day-13-lovina-beach-bali.md","_extension":"md"}]