[{"_path":"/japan-2014/tickets-geboekt","title":"Tickets geboekt, Tokyo Japan!","excerpt":"Na lang zoeken en vergelijken, hebben we de tickets naar Japan geboekt.","date":"2014-03-14","category":"Tokyo, Kyoto, Osaka - Japan"},{"_path":"/japan-2014/tokyo-international-airport-haneda","title":"Tokyo International Airport, Haneda","excerpt":"De vlucht van Nederland naar Japan ging vrijwel probleemloos, totdat ik op Schiphol werd aangehouden vanwege mijn achternaam. Ik dacht echt...","date":"2014-09-14","category":"Tokyo, Kyoto, Osaka - Japan"}]