{"hash":"ec5e50c96b423917fd23f8317f4a3bf99d08681d","data":{"category":{"title":"Goreme, Antalya, Istanbul - Turkije","path":"/blog/goreme-antalya-istanbul-turkije/","belongsTo":{"edges":[{"node":{"title":"Goreme","excerpt":"Goreme ook wel bekend voor de 'Insta' luchtbalonnen en mooie landschappen.","image":"https://www.danhnguyen.nl/wp-content/uploads/20220930_175421.jpg","path":"/blog/turkije-2022/goreme/","date":"2022-09-30","intro":"Laatste jaar dat we met onze dochter buiten de schoolvakanties kunnen reizen. Dit keer gaan we naar Turkije. We komen langs plekken zoals Goreme, Antalya en Istanbul.","category":{"id":"Goreme, Antalya, Istanbul - Turkije","title":"Goreme, Antalya, Istanbul - Turkije"}}},{"node":{"title":"Antalya","excerpt":"Lekker toerist spelen en genieten van het lekkere weer.","image":"https://www.danhnguyen.nl/wp-content/uploads/20221008_072151.jpg","path":"/blog/turkije-2022/antalya/","date":"2022-10-05","intro":"","category":{"id":"Goreme, Antalya, Istanbul - Turkije","title":"Goreme, Antalya, Istanbul - Turkije"}}},{"node":{"title":"Istanbul","excerpt":"Istanbul. Druk.","image":"https://www.danhnguyen.nl/wp-content/uploads/20221011_110129.jpg","path":"/blog/turkije-2022/istanbul/","date":"2022-10-10","intro":"","category":{"id":"Goreme, Antalya, Istanbul - Turkije","title":"Goreme, Antalya, Istanbul - Turkije"}}}]}}},"context":{}}